s1290006_learn/__init__.py
s1290006_learn/main.py
s1290006_learn/statistcs/__init__.py
s1290006_learn/statistcs/frequenciesOfItems.py
s1290006_learn/visualization/__init__.py
s1290006_learn/visualization/heatMapItemsFrequencies.py
s1290006_learn-0.0.1.dist-info/METADATA
s1290006_learn-0.0.1.dist-info/WHEEL
s1290006_learn-0.0.1.dist-info/top_level.txt
s1290006_learn-0.0.1.dist-info/RECORD
