Metadata-Version: 2.1
Name: s1290006_learn
Version: 0.0.1
Summary: heat map pm25
Home-page: https://github.com/s1290006/s1290006_learn
Author: s1290006
Author-email: s1290006@u-aizu.ac.jp
License: UNKNOWN
Platform: UNKNOWN
Classifier: Programming Language :: Python :: 3.7
Classifier: License :: OSI Approved :: MIT License
Classifier: Operating System :: OS Independent
